certbot_dns_schlundtech/__init__.py
certbot_dns_schlundtech/dns_schlundtech.py
certbot_dns_schlundtech/dns_schlundtech_test.py
certbot_dns_schlundtech-0.5.0.dist-info/LICENSE
certbot_dns_schlundtech-0.5.0.dist-info/METADATA
certbot_dns_schlundtech-0.5.0.dist-info/WHEEL
certbot_dns_schlundtech-0.5.0.dist-info/entry_points.txt
certbot_dns_schlundtech-0.5.0.dist-info/top_level.txt
certbot_dns_schlundtech-0.5.0.dist-info/RECORD
