Metadata-Version: 2.1
Name: certbot-dns-schlundtech
Version: 0.5.0
Summary: SchlundTech XML Gateway DNS Authenticator plugin for Certbot
Home-page: https://github.com/couchtyp/certbot-dns-schlundtech
Author: Philipp Mueller
Author-email: pmueller@maildir.eu
License: MIT License
Classifier: Development Status :: 4 - Beta
Classifier: Environment :: Plugins
Classifier: Intended Audience :: System Administrators
Classifier: License :: OSI Approved :: Apache Software License
Classifier: Operating System :: POSIX :: Linux
Classifier: Programming Language :: Python
Classifier: Programming Language :: Python :: 2
Classifier: Programming Language :: Python :: 2.7
Classifier: Programming Language :: Python :: 3
Classifier: Programming Language :: Python :: 3.6
Classifier: Programming Language :: Python :: 3.7
Classifier: Topic :: Internet :: WWW/HTTP
Classifier: Topic :: Security
Classifier: Topic :: System :: Installation/Setup
Classifier: Topic :: System :: Networking
Classifier: Topic :: System :: Systems Administration
Classifier: Topic :: Utilities
Requires-Python: >=2.7, !=3.0.*, !=3.1.*, !=3.2.*, !=3.3.*
License-File: LICENSE
Requires-Dist: acme (>=0.29.0)
Requires-Dist: certbot (>=1.0.0)
Requires-Dist: mock
Requires-Dist: setuptools
Requires-Dist: zope.interface
Provides-Extra: docs
